{
  "format": "idx_val_memmap_v1",
  "index_file": "C:\\Users\\laraa\\OneDrive\\Desktop\\portf\\developer-portfolio-main\\LEO\\python\\..\\outputs\\weights_indices_run.bin",
  "value_file": "C:\\Users\\laraa\\OneDrive\\Desktop\\portf\\developer-portfolio-main\\LEO\\python\\..\\outputs\\weights_values_run.bin",
  "index_dtype": "int32",
  "value_dtype": "float32",
  "layers": [
    {
      "name": "conv1",
      "kind": "conv",
      "out_channels": 8,
      "in_channels": 1,
      "kernel": [
        3,
        3
      ],
      "stride": [
        1,
        1
      ],
      "padding": [
        1,
        1
      ],
      "out_hw": [
        16,
        16
      ],
      "base_offset": 0,
      "bias": [
        -0.17792104184627533,
        0.10448617488145828,
        0.4333422780036926,
        0.2300296574831009,
        -0.030106104910373688,
        0.03447580337524414,
        0.33033809065818787,
        0.41401419043540955
      ],
      "channel_segments": [
        {
          "offset": 0,
          "length": 5
        },
        {
          "offset": 5,
          "length": 4
        },
        {
          "offset": 9,
          "length": 6
        },
        {
          "offset": 15,
          "length": 7
        },
        {
          "offset": 22,
          "length": 7
        },
        {
          "offset": 29,
          "length": 4
        },
        {
          "offset": 33,
          "length": 6
        },
        {
          "offset": 39,
          "length": 5
        }
      ],
      "dense_weights": 72
    },
    {
      "name": "conv2",
      "kind": "conv",
      "out_channels": 16,
      "in_channels": 8,
      "kernel": [
        3,
        3
      ],
      "stride": [
        1,
        1
      ],
      "padding": [
        1,
        1
      ],
      "out_hw": [
        16,
        16
      ],
      "base_offset": 44,
      "bias": [
        0.07226840406656265,
        0.1962277740240097,
        -0.1164916604757309,
        0.12574972212314606,
        -0.006656645331531763,
        -0.04317440837621689,
        -0.13566069304943085,
        -0.13744084537029266,
        0.08785166591405869,
        0.14929552376270294,
        0.14408518373966217,
        0.019867990165948868,
        0.032034385949373245,
        0.14307796955108643,
        0.13620063662528992,
        0.0972735658288002
      ],
      "channel_segments": [
        {
          "offset": 0,
          "length": 19
        },
        {
          "offset": 19,
          "length": 32
        },
        {
          "offset": 51,
          "length": 5
        },
        {
          "offset": 56,
          "length": 23
        },
        {
          "offset": 79,
          "length": 25
        },
        {
          "offset": 104,
          "length": 16
        },
        {
          "offset": 120,
          "length": 8
        },
        {
          "offset": 128,
          "length": 6
        },
        {
          "offset": 134,
          "length": 39
        },
        {
          "offset": 173,
          "length": 37
        },
        {
          "offset": 210,
          "length": 34
        },
        {
          "offset": 244,
          "length": 18
        },
        {
          "offset": 262,
          "length": 23
        },
        {
          "offset": 285,
          "length": 26
        },
        {
          "offset": 311,
          "length": 31
        },
        {
          "offset": 342,
          "length": 29
        }
      ],
      "dense_weights": 1152
    },
    {
      "name": "fc",
      "kind": "linear",
      "out_channels": 2,
      "in_channels": 256,
      "kernel": [
        1,
        1
      ],
      "stride": [
        1,
        1
      ],
      "padding": [
        0,
        0
      ],
      "out_hw": [
        1,
        1
      ],
      "base_offset": 415,
      "bias": [
        0.02482316642999649,
        0.04039023444056511
      ],
      "channel_segments": [
        {
          "offset": 0,
          "length": 53
        },
        {
          "offset": 53,
          "length": 53
        }
      ],
      "dense_weights": 512
    }
  ],
  "total_nonzero": 521
}